pynwn.cpython-38-x86_64-linux-gnu.so
pynwn-0.1.dev0.dist-info/LICENSE
pynwn-0.1.dev0.dist-info/top_level.txt
pynwn-0.1.dev0.dist-info/WHEEL
pynwn-0.1.dev0.dist-info/RECORD
pynwn-0.1.dev0.dist-info/METADATA
