Metadata-Version: 2.1
Name: pynwn
Version: 0.1.dev0
Summary: libnw wrapper
Author: jmd
Author-email: joshua.m.dean@gmail.com
Requires-Python: >=3.8
Provides-Extra: test
License-File: LICENSE
